<?xml version="1.0" encoding="UTF-8"?>
<metadata xml:lang="en"><Esri><CreaDate>20150323</CreaDate><CreaTime>10584900</CreaTime><ArcGISFormat>1.0</ArcGISFormat><SyncOnce>TRUE</SyncOnce><DataProperties><lineage><Process ToolSource="c:\program files (x86)\arcgis\desktop10.1\ArcToolbox\Toolboxes\Data Management Tools.tbx\Project" Date="20150218" Time="160618">Project C:\_doutorado_sig\resultados\d_ant_a.shp C:\_doutorado_sig\resultados\d_ant_a_utm.shp PROJCS['WGS_1984_UTM_Zone_23S',GEOGCS['GCS_WGS_1984',DATUM['D_WGS_1984',SPHEROID['WGS_1984',6378137.0,298.257223563]],PRIMEM['Greenwich',0.0],UNIT['Degree',0.0174532925199433]],PROJECTION['Transverse_Mercator'],PARAMETER['False_Easting',500000.0],PARAMETER['False_Northing',10000000.0],PARAMETER['Central_Meridian',-45.0],PARAMETER['Scale_Factor',0.9996],PARAMETER['Latitude_Of_Origin',0.0],UNIT['Meter',1.0]] # GEOGCS['GCS_WGS_1984',DATUM['D_WGS_1984',SPHEROID['WGS_1984',6378137.0,298.257223563]],PRIMEM['Greenwich',0.0],UNIT['Degree',0.0174532925199433]]</Process></lineage><itemProps><itemLocation><linkage Sync="TRUE">file://\\DANI_PC\C$\_doutorado_sig\resultados\shapes_pontos\d1_lui_d_utm</linkage><protocol Sync="TRUE">Local Area Network</protocol></itemLocation></itemProps><copyHistory><copy source="C:\_doutorado_sig\resultados\d1_lui_d_utm" dest="\\DANI_PC\C$\_doutorado_sig\resultados\shapes_pontos\d1_lui_d_utm" date="20150323" time="10584900"></copy></copyHistory></DataProperties></Esri><idinfo><citation><citeinfo><onlink Sync="TRUE">\\PC5\H\doc\resultados\d_lui_b_utmCopy</onlink></citeinfo></citation></idinfo><distInfo><distributor><distorTran><onLineSrc><linkage Sync="TRUE">file://\\PC5\H\doc\resultados\d_lui_b_utmCopy</linkage><protocol Sync="TRUE">Local Area Network</protocol></onLineSrc></distorTran></distributor></distInfo><dataqual><lineage><procstep><procdesc Sync="TRUE">Dataset copied.</procdesc><srcused Sync="TRUE">H:\doc\resultados\d_lui_b_utm</srcused><procdate Sync="TRUE">20150319</procdate><proctime Sync="TRUE">09425700</proctime></procstep></lineage></dataqual></metadata>
